[
  {
    "run_id": "llama2-7b_1377_1_prefill",
    "gpu_freq_mhz": 1377,
    "max_num_seqs": 1,
    "phase": "prefill",
    "input_mean": 1000.0,
    "output_mean": 50.0,
    "steady_state_energy_j": 20238.110000000102,
    "steady_state_energy_per_token_j": 5.358249933809929,
    "steady_state_duration_s": 94.27071980300025,
    "mean_e2el_ms": 942.6190534999114,
    "p50_e2el_ms": 1170.7495765003841,
    "p99_e2el_ms": 1183.25292204996,
    "mean_ttft_ms": 219.699070651576,
    "p99_ttft_ms": 239.64830412063748,
    "request_throughput": 1.0607747581536702,
    "output_throughput": 40.06546261546413,
    "avg_gpu_temp_c": 52.31578947368421,
    "temp_before_c": 49,
    "temp_after_c": 46
  },
  {
    "run_id": "llama2-7b_1200_1_prefill",
    "gpu_freq_mhz": 1200,
    "max_num_seqs": 1,
    "phase": "prefill",
    "input_mean": 1000.0,
    "output_mean": 50.0,
    "steady_state_energy_j": 21314.56599999999,
    "steady_state_energy_per_token_j": 5.273272142503709,
    "steady_state_duration_s": 99.56058475499958,
    "mean_e2el_ms": 995.5187230000593,
    "p50_e2el_ms": 1175.688914499915,
    "p99_e2el_ms": 1183.4352558697537,
    "mean_ttft_ms": 220.4813119999591,
    "p99_ttft_ms": 259.1391070208192,
    "request_throughput": 1.00441354624505,
    "output_throughput": 40.598395539224924,
    "avg_gpu_temp_c": 54.6,
    "temp_before_c": 53,
    "temp_after_c": 49
  },
  {
    "run_id": "llama2-7b_1000_1_prefill",
    "gpu_freq_mhz": 1000,
    "max_num_seqs": 1,
    "phase": "prefill",
    "input_mean": 1000.0,
    "output_mean": 50.0,
    "steady_state_energy_j": 21514.120999999926,
    "steady_state_energy_per_token_j": 5.266614687882479,
    "steady_state_duration_s": 100.27101565300109,
    "mean_e2el_ms": 1002.623210120073,
    "p50_e2el_ms": 1175.1764020000337,
    "p99_e2el_ms": 1183.1888803906622,
    "mean_ttft_ms": 219.53738283523958,
    "p99_ttft_ms": 223.57158189952315,
    "request_throughput": 0.9972971685662488,
    "output_throughput": 40.739589335931264,
    "avg_gpu_temp_c": 54.80952380952381,
    "temp_before_c": 55,
    "temp_after_c": 43
  },
  {
    "run_id": "llama2-7b_780_1_prefill",
    "gpu_freq_mhz": 780,
    "max_num_seqs": 1,
    "phase": "prefill",
    "input_mean": 1000.0,
    "output_mean": 50.0,
    "steady_state_energy_j": 20701.472999999998,
    "steady_state_energy_per_token_j": 5.342315612903225,
    "steady_state_duration_s": 96.17714528000033,
    "mean_e2el_ms": 961.6845310399731,
    "p50_e2el_ms": 1173.7795005001317,
    "p99_e2el_ms": 1182.0258466802625,
    "mean_ttft_ms": 219.60382118076984,
    "p99_ttft_ms": 224.41340863926584,
    "request_throughput": 1.039748057699885,
    "output_throughput": 40.29023723587054,
    "avg_gpu_temp_c": 54.65,
    "temp_before_c": 53,
    "temp_after_c": 43
  },
  {
    "run_id": "llama2-7b_1377_1_decode",
    "gpu_freq_mhz": 1377,
    "max_num_seqs": 1,
    "phase": "decode",
    "input_mean": 50.0,
    "output_mean": 500.0,
    "steady_state_energy_j": 126907.71899999992,
    "steady_state_energy_per_token_j": 4.371756484894413,
    "steady_state_duration_s": 545.4829094430006,
    "mean_e2el_ms": 5454.716799619855,
    "p50_e2el_ms": 5432.135348500196,
    "p99_e2el_ms": 9384.84781180965,
    "mean_ttft_ms": 36.968806849963585,
    "p99_ttft_ms": 38.818662679914276,
    "request_throughput": 0.183323800377378,
    "output_throughput": 53.21706601154906,
    "avg_gpu_temp_c": 56.872727272727275,
    "temp_before_c": 47,
    "temp_after_c": 45
  },
  {
    "run_id": "llama2-7b_1200_1_decode",
    "gpu_freq_mhz": 1200,
    "max_num_seqs": 1,
    "phase": "decode",
    "input_mean": 50.0,
    "output_mean": 500.0,
    "steady_state_energy_j": 126724.71800000011,
    "steady_state_energy_per_token_j": 4.36545240965931,
    "steady_state_duration_s": 545.4322933099993,
    "mean_e2el_ms": 5454.225148459918,
    "p50_e2el_ms": 5431.891297998845,
    "p99_e2el_ms": 9381.058567948785,
    "mean_ttft_ms": 36.862052510023204,
    "p99_ttft_ms": 39.336140161049116,
    "request_throughput": 0.18334081283149195,
    "output_throughput": 53.2220045568538,
    "avg_gpu_temp_c": 56.67272727272727,
    "temp_before_c": 47,
    "temp_after_c": 45
  },
  {
    "run_id": "llama2-7b_1000_1_decode",
    "gpu_freq_mhz": 1000,
    "max_num_seqs": 1,
    "phase": "decode",
    "input_mean": 50.0,
    "output_mean": 500.0,
    "steady_state_energy_j": 119951.57199999993,
    "steady_state_energy_per_token_j": 4.837732284734822,
    "steady_state_duration_s": 767.6076252790008,
    "mean_e2el_ms": 4914.936444978919,
    "p50_e2el_ms": 3412.841721001314,
    "p99_e2el_ms": 9381.683748839132,
    "mean_ttft_ms": 36.82030604198333,
    "p99_ttft_ms": 38.55625156000315,
    "request_throughput": 0.12376114680396842,
    "output_throughput": 32.30165931583576,
    "avg_gpu_temp_c": 45.57142857142857,
    "temp_before_c": 57,
    "temp_after_c": 23
  },
  {
    "run_id": "llama2-7b_780_1_decode",
    "gpu_freq_mhz": 780,
    "max_num_seqs": 1,
    "phase": "decode",
    "input_mean": 50.0,
    "output_mean": 500.0,
    "steady_state_energy_j": 126815.55000000005,
    "steady_state_energy_per_token_j": 4.36858141858142,
    "steady_state_duration_s": 545.7618503659996,
    "mean_e2el_ms": 5457.5117992499145,
    "p50_e2el_ms": 5435.754092500247,
    "p99_e2el_ms": 9389.006388551024,
    "mean_ttft_ms": 36.99337720998301,
    "p99_ttft_ms": 40.296967749418414,
    "request_throughput": 0.18323010289733122,
    "output_throughput": 53.18986657006628,
    "avg_gpu_temp_c": 56.53636363636364,
    "temp_before_c": 47,
    "temp_after_c": 45
  },
  {
    "run_id": "llama2-7b_1377_8_prefill",
    "gpu_freq_mhz": 1377,
    "max_num_seqs": 8,
    "phase": "prefill",
    "input_mean": 1000.0,
    "output_mean": 50.0,
    "steady_state_energy_j": 7898.5190000000875,
    "steady_state_energy_per_token_j": 1.9935686521958829,
    "steady_state_duration_s": 36.01485871499972,
    "mean_e2el_ms": 2843.4862791098385,
    "p50_e2el_ms": 3322.197671998765,
    "p99_e2el_ms": 4240.259570129892,
    "mean_ttft_ms": 575.1664187607433,
    "p99_ttft_ms": 1755.9132781285552,
    "request_throughput": 2.776631745006716,
    "output_throughput": 110.01014973716609,
    "avg_gpu_temp_c": 51,
    "temp_before_c": 47,
    "temp_after_c": 41
  },
  {
    "run_id": "llama2-7b_1200_8_prefill",
    "gpu_freq_mhz": 1200,
    "max_num_seqs": 8,
    "phase": "prefill",
    "input_mean": 1000.0,
    "output_mean": 50.0,
    "steady_state_energy_j": 7886.721999999834,
    "steady_state_energy_per_token_j": 2.0405490297541613,
    "steady_state_duration_s": 35.92087624600026,
    "mean_e2el_ms": 2816.358195510038,
    "p50_e2el_ms": 3341.5155820002838,
    "p99_e2el_ms": 4218.169149740406,
    "mean_ttft_ms": 392.87797184446794,
    "p99_ttft_ms": 1338.0207262399924,
    "request_throughput": 2.783896453838173,
    "output_throughput": 107.59759794084539,
    "avg_gpu_temp_c": 52.75,
    "temp_before_c": 51,
    "temp_after_c": 44
  },
  {
    "run_id": "llama2-7b_1000_8_prefill",
    "gpu_freq_mhz": 1000,
    "max_num_seqs": 8,
    "phase": "prefill",
    "input_mean": 1000.0,
    "output_mean": 50.0,
    "steady_state_energy_j": 8008.716000000015,
    "steady_state_energy_per_token_j": 2.0383598880122205,
    "steady_state_duration_s": 35.78530550600044,
    "mean_e2el_ms": 2827.765371410005,
    "p50_e2el_ms": 3355.8637679998355,
    "p99_e2el_ms": 4013.8095090108254,
    "mean_ttft_ms": 579.6864076264183,
    "p99_ttft_ms": 1575.5255400994417,
    "request_throughput": 2.7944430985291464,
    "output_throughput": 109.79366934121016,
    "avg_gpu_temp_c": 54.25,
    "temp_before_c": 52,
    "temp_after_c": 43
  },
  {
    "run_id": "llama2-7b_780_8_prefill",
    "gpu_freq_mhz": 780,
    "max_num_seqs": 8,
    "phase": "prefill",
    "input_mean": 1000.0,
    "output_mean": 50.0,
    "steady_state_energy_j": 7668.445999999996,
    "steady_state_energy_per_token_j": 2.1456200335758244,
    "steady_state_duration_s": 34.60937619300057,
    "mean_e2el_ms": 2734.0973525298796,
    "p50_e2el_ms": 3316.965449000236,
    "p99_e2el_ms": 4677.65402090914,
    "mean_ttft_ms": 498.4272365243935,
    "p99_ttft_ms": 1759.1715887498685,
    "request_throughput": 2.8893904195887843,
    "output_throughput": 103.26681359610315,
    "avg_gpu_temp_c": 54.57142857142857,
    "temp_before_c": 52,
    "temp_after_c": 49
  },
  {
    "run_id": "llama2-7b_1377_8_decode",
    "gpu_freq_mhz": 1377,
    "max_num_seqs": 8,
    "phase": "decode",
    "input_mean": 50.0,
    "output_mean": 500.0,
    "steady_state_energy_j": 20783.9580000001,
    "steady_state_energy_per_token_j": 0.6882561096761408,
    "steady_state_duration_s": 96.46598006899876,
    "mean_e2el_ms": 7326.295988789971,
    "p50_e2el_ms": 8047.3252094998315,
    "p99_e2el_ms": 12245.336116207363,
    "mean_ttft_ms": 63.01558286020736,
    "p99_ttft_ms": 130.86842833050468,
    "request_throughput": 1.0366348833907402,
    "output_throughput": 313.0430020863357,
    "avg_gpu_temp_c": 54.55,
    "temp_before_c": 54,
    "temp_after_c": 44
  },
  {
    "run_id": "llama2-7b_1200_8_decode",
    "gpu_freq_mhz": 1200,
    "max_num_seqs": 8,
    "phase": "decode",
    "input_mean": 50.0,
    "output_mean": 500.0,
    "steady_state_energy_j": 18865.06799999997,
    "steady_state_energy_per_token_j": 0.6977758544163327,
    "steady_state_duration_s": 88.17352766100157,
    "mean_e2el_ms": 6568.5230809300265,
    "p50_e2el_ms": 5999.643873999958,
    "p99_e2el_ms": 12398.136151330109,
    "mean_ttft_ms": 74.88177130988333,
    "p99_ttft_ms": 273.38471734761697,
    "request_throughput": 1.1341272449081017,
    "output_throughput": 306.6226419333544,
    "avg_gpu_temp_c": 54,
    "temp_before_c": 53,
    "temp_after_c": 46
  },
  {
    "run_id": "llama2-7b_1000_8_decode",
    "gpu_freq_mhz": 1000,
    "max_num_seqs": 8,
    "phase": "decode",
    "input_mean": 50.0,
    "output_mean": 500.0,
    "steady_state_energy_j": 23110.212000000058,
    "steady_state_energy_per_token_j": 0.6747704166545025,
    "steady_state_duration_s": 109.0124952949991,
    "mean_e2el_ms": 8272.870341919806,
    "p50_e2el_ms": 11032.717587000661,
    "p99_e2el_ms": 12271.093909440497,
    "mean_ttft_ms": 65.02334355984203,
    "p99_ttft_ms": 132.28317709144903,
    "request_throughput": 0.9173260343173473,
    "output_throughput": 314.17499349334827,
    "avg_gpu_temp_c": 48.45454545454545,
    "temp_before_c": 39,
    "temp_after_c": 46
  },
  {
    "run_id": "llama2-7b_780_8_decode",
    "gpu_freq_mhz": 780,
    "max_num_seqs": 8,
    "phase": "decode",
    "input_mean": 50.0,
    "output_mean": 500.0,
    "steady_state_energy_j": 19233.824999999953,
    "steady_state_energy_per_token_j": 0.6810362226471196,
    "steady_state_duration_s": 89.69007284299732,
    "mean_e2el_ms": 6868.366708529975,
    "p50_e2el_ms": 6111.772084501354,
    "p99_e2el_ms": 12323.133135181015,
    "mean_ttft_ms": 62.048530579886574,
    "p99_ttft_ms": 119.67828148048284,
    "request_throughput": 1.114950594086931,
    "output_throughput": 314.8843467820311,
    "avg_gpu_temp_c": 53.666666666666664,
    "temp_before_c": 53,
    "temp_after_c": 50
  },
  {
    "run_id": "llama2-7b_1377_32_prefill",
    "gpu_freq_mhz": 1377,
    "max_num_seqs": 32,
    "phase": "prefill",
    "input_mean": 1000.0,
    "output_mean": 50.0,
    "steady_state_energy_j": 6862.239999999991,
    "steady_state_energy_per_token_j": 1.801112860892386,
    "steady_state_duration_s": 29.40096061999793,
    "mean_e2el_ms": 8895.291044300175,
    "p50_e2el_ms": 9622.135781501129,
    "p99_e2el_ms": 16054.70963553089,
    "mean_ttft_ms": 3813.931698318861,
    "p99_ttft_ms": 7064.451005302543,
    "request_throughput": 3.4012494112856313,
    "output_throughput": 129.58760256998255,
    "avg_gpu_temp_c": 50.666666666666664,
    "temp_before_c": 46,
    "temp_after_c": 46
  },
  {
    "run_id": "llama2-7b_1200_32_prefill",
    "gpu_freq_mhz": 1200,
    "max_num_seqs": 32,
    "phase": "prefill",
    "input_mean": 1000.0,
    "output_mean": 50.0,
    "steady_state_energy_j": 6593.548000000184,
    "steady_state_energy_per_token_j": 1.9800444444444998,
    "steady_state_duration_s": 28.210201941001287,
    "mean_e2el_ms": 8652.56444469007,
    "p50_e2el_ms": 9163.312991999192,
    "p99_e2el_ms": 16389.48129173227,
    "mean_ttft_ms": 3593.9347047296264,
    "p99_ttft_ms": 6948.605387318674,
    "request_throughput": 3.5448168789836965,
    "output_throughput": 118.0424020701571,
    "avg_gpu_temp_c": 54.833333333333336,
    "temp_before_c": 52,
    "temp_after_c": 46
  },
  {
    "run_id": "llama2-7b_1000_32_prefill",
    "gpu_freq_mhz": 1000,
    "max_num_seqs": 32,
    "phase": "prefill",
    "input_mean": 1000.0,
    "output_mean": 50.0,
    "steady_state_energy_j": 6980.487999999896,
    "steady_state_energy_per_token_j": 1.8187826993225367,
    "steady_state_duration_s": 29.95585823899819,
    "mean_e2el_ms": 8975.392598699946,
    "p50_e2el_ms": 8866.901052499088,
    "p99_e2el_ms": 18010.5850494908,
    "mean_ttft_ms": 4111.218261677803,
    "p99_ttft_ms": 8958.442428580383,
    "request_throughput": 3.338245200727198,
    "output_throughput": 128.12185080390987,
    "avg_gpu_temp_c": 55.833333333333336,
    "temp_before_c": 54,
    "temp_after_c": 53
  },
  {
    "run_id": "llama2-7b_780_32_prefill",
    "gpu_freq_mhz": 780,
    "max_num_seqs": 32,
    "phase": "prefill",
    "input_mean": 1000.0,
    "output_mean": 50.0,
    "steady_state_energy_j": 7008.5779999999795,
    "steady_state_energy_per_token_j": 1.6827318127250852,
    "steady_state_duration_s": 30.089244897000754,
    "mean_e2el_ms": 9038.925139960047,
    "p50_e2el_ms": 8432.349808001163,
    "p99_e2el_ms": 16602.6106953315,
    "mean_ttft_ms": 4191.390887158003,
    "p99_ttft_ms": 9076.413277618121,
    "request_throughput": 3.3234466448829973,
    "output_throughput": 138.42155275937682,
    "avg_gpu_temp_c": 56.714285714285715,
    "temp_before_c": 56,
    "temp_after_c": 44
  },
  {
    "run_id": "llama2-7b_1377_32_decode",
    "gpu_freq_mhz": 1377,
    "max_num_seqs": 32,
    "phase": "decode",
    "input_mean": 50.0,
    "output_mean": 500.0,
    "steady_state_energy_j": 8739.446999999927,
    "steady_state_energy_per_token_j": 0.2781137665478592,
    "steady_state_duration_s": 38.97215047300051,
    "mean_e2el_ms": 10368.770977259956,
    "p50_e2el_ms": 11093.047607499102,
    "p99_e2el_ms": 17290.796829632018,
    "mean_ttft_ms": 154.38594324001315,
    "p99_ttft_ms": 355.67794901046,
    "request_throughput": 2.565934873654943,
    "output_throughput": 806.3193746973293,
    "avg_gpu_temp_c": 54.875,
    "temp_before_c": 53,
    "temp_after_c": 48
  },
  {
    "run_id": "llama2-7b_1200_32_decode",
    "gpu_freq_mhz": 1200,
    "max_num_seqs": 32,
    "phase": "decode",
    "input_mean": 50.0,
    "output_mean": 500.0,
    "steady_state_energy_j": 8476.69200000004,
    "steady_state_energy_per_token_j": 0.27463768022031554,
    "steady_state_duration_s": 37.71851326500109,
    "mean_e2el_ms": 10091.40100521985,
    "p50_e2el_ms": 10975.80662549808,
    "p99_e2el_ms": 17168.707245780606,
    "mean_ttft_ms": 168.24430742988625,
    "p99_ttft_ms": 358.49963722139364,
    "request_throughput": 2.651217965496793,
    "output_throughput": 818.2984250505851,
    "avg_gpu_temp_c": 55.625,
    "temp_before_c": 54,
    "temp_after_c": 47
  },
  {
    "run_id": "llama2-7b_1000_32_decode",
    "gpu_freq_mhz": 1000,
    "max_num_seqs": 32,
    "phase": "decode",
    "input_mean": 50.0,
    "output_mean": 500.0,
    "steady_state_energy_j": 8598.196999999927,
    "steady_state_energy_per_token_j": 0.266908704290058,
    "steady_state_duration_s": 38.37276149600075,
    "mean_e2el_ms": 10568.43969496993,
    "p50_e2el_ms": 14436.448541500795,
    "p99_e2el_ms": 16986.677865348138,
    "mean_ttft_ms": 161.69293817969447,
    "p99_ttft_ms": 357.81499896784226,
    "request_throughput": 2.606015207178199,
    "output_throughput": 839.501738840385,
    "avg_gpu_temp_c": 45.375,
    "temp_before_c": 39,
    "temp_after_c": 41
  },
  {
    "run_id": "llama2-7b_780_32_decode",
    "gpu_freq_mhz": 780,
    "max_num_seqs": 32,
    "phase": "decode",
    "input_mean": 50.0,
    "output_mean": 500.0,
    "steady_state_energy_j": 8161.948000000091,
    "steady_state_energy_per_token_j": 0.27493340519419585,
    "steady_state_duration_s": 36.46275448899905,
    "mean_e2el_ms": 9782.096638060139,
    "p50_e2el_ms": 12635.887410999203,
    "p99_e2el_ms": 17082.292646430433,
    "mean_ttft_ms": 156.41231449015322,
    "p99_ttft_ms": 361.60004351964744,
    "request_throughput": 2.7425245679168415,
    "output_throughput": 814.1732684774727,
    "avg_gpu_temp_c": 52,
    "temp_before_c": 50,
    "temp_after_c": 42
  }
]